async_websocket_client/__init__.py
async_websocket_client/apps.py
async_websocket_client/dispatchers.py
async_websocket_client-0.1.0.dist-info/LICENSE
async_websocket_client-0.1.0.dist-info/METADATA
async_websocket_client-0.1.0.dist-info/WHEEL
async_websocket_client-0.1.0.dist-info/RECORD
