Metadata-Version: 2.1
Name: async-websocket-client
Version: 0.1.0
Summary: 
Author: irocshers
Author-email: develop.iam@rocshers.com
Requires-Python: >=3.8,<4.0
Classifier: Programming Language :: Python :: 3
Classifier: Programming Language :: Python :: 3.8
Classifier: Programming Language :: Python :: 3.9
Classifier: Programming Language :: Python :: 3.10
Classifier: Programming Language :: Python :: 3.11
Classifier: Topic :: Software Development :: Libraries :: Python Modules
Requires-Dist: websockets (>=11.0.2,<12.0.0)
